OperationBattleshipJobCategoryClassifier/JobCategoryClassifierBertInference.py
OperationBattleshipJobCategoryClassifier/JobCategoryClassifierBertTraining.py
OperationBattleshipJobCategoryClassifier/__init__.py
tests/__init__.py
tests/test.py
OperationBattleshipJobCategoryClassifier-0.1.0.dist-info/LICENSE
OperationBattleshipJobCategoryClassifier-0.1.0.dist-info/METADATA
OperationBattleshipJobCategoryClassifier-0.1.0.dist-info/WHEEL
OperationBattleshipJobCategoryClassifier-0.1.0.dist-info/top_level.txt
OperationBattleshipJobCategoryClassifier-0.1.0.dist-info/RECORD
