Metadata-Version: 2.1
Name: OperationBattleshipJobCategoryClassifier
Version: 0.1.0
Summary: A package for classifying job categories using BERT.
Home-page: https://github.com/yourusername/OperationBattleshipJobCategoryClassifier
Author: Matthew Caraway
Author-email: your.email@example.com
Classifier: Programming Language :: Python :: 3
Classifier: License :: OSI Approved :: MIT License
Classifier: Operating System :: OS Independent
Requires-Python: >=3.6
License-File: LICENSE
